tuhinga.py
tuhinga-0.1.1.dist-info/WHEEL
tuhinga-0.1.1.dist-info/top_level.txt
tuhinga-0.1.1.dist-info/METADATA
tuhinga-0.1.1.dist-info/metadata.json
tuhinga-0.1.1.dist-info/DESCRIPTION.rst
tuhinga-0.1.1.dist-info/RECORD
tuhinga-0.1.1.data/data/share/tuhinga/LICENSE
tuhinga-0.1.1.data/data/share/tuhinga/README.rst
tuhinga-0.1.1.data/data/share/tuhinga/tuhinga_webrepl.py
tuhinga-0.1.1.data/data/share/tuhinga/tuh.vim
tuhinga-0.1.1.data/data/share/tuhinga/examples/very-minimal.tuh
tuhinga-0.1.1.data/data/share/tuhinga/examples/pretty-minimal.tuh
tuhinga-0.1.1.data/data/share/tuhinga/examples/dev-test.tuh
tuhinga-0.1.1.data/data/share/tuhinga/examples/bootstrap-navbar.tuh
tuhinga-0.1.1.data/scripts/tuh
