Metadata-Version: 2.0
Name: tuhinga
Version: 0.1.1
Summary: Minimalistic markup language that translates to XML/HTML
Home-page: http://github.com/babab/tuhinga
Author: Benjamin Althues
Author-email: benjamin@babab.nl
License: ISC
Download-URL: https://pypi.python.org/pypi/tuhinga
Platform: any
Classifier: Development Status :: 4 - Beta
Classifier: Environment :: Console
Classifier: Environment :: Web Environment
Classifier: Intended Audience :: Developers
Classifier: Intended Audience :: End Users/Desktop
Classifier: Intended Audience :: Information Technology
Classifier: Intended Audience :: System Administrators
Classifier: License :: OSI Approved :: ISC License (ISCL)
Classifier: Natural Language :: English
Classifier: Operating System :: POSIX
Classifier: Operating System :: Unix
Classifier: Programming Language :: Python :: 2.7
Classifier: Programming Language :: Python :: 3
Classifier: Topic :: Adaptive Technologies
Classifier: Topic :: Documentation
Classifier: Topic :: Internet
Classifier: Topic :: Internet :: WWW/HTTP
Classifier: Topic :: Office/Business
Classifier: Topic :: Text Editors :: Documentation
Classifier: Topic :: Text Editors :: Text Processing
Classifier: Topic :: Text Processing :: Filters
Classifier: Topic :: Text Processing :: Linguistic
Classifier: Topic :: Text Processing :: Markup :: HTML
Classifier: Topic :: Text Processing :: Markup :: XML
Classifier: Topic :: Utilities
